Workbook

Sheet 📋 Portada
A1: TALLER 5 – ÍNDICE ECONÓMICO GLOBAL ANTES Y DESPUÉS DEL COVID
A2: Energy · Materials · Financials | 2015–2025 | Bloomberg
A4: 1 | B4: 📊 Datos Acciones
B5: Precios de cierre y volúmenes diarios de 10 acciones (3 sectores) 2015–2025. Descarga desde Bloomberg con BDH(ticker, "PX_LAST", ini, fin) y BDH(..., "PX_VOLUME").
A8: 2 | B8: ⚖️ Pesos Índice
B9: a) Pesos por volumen ene-2015 (verificar suma=1) b) Pesos por precio ene-2015 → comparar y analizar diferencias
A12: 3 | B12: 📈 Retornos + 📊 Gráficos
B13: Retornos aritméticos diarios · Box & Whisker · Histograma · Línea Base 100
A16: 4 | B16: 🦠 Análisis COVID
B17: Desv. estándar · N observaciones · IC 95% (CONFIDENCE.T) · Barras con IC · Interpretación

Sheet 📊 Datos Acciones
A1: PRECIOS DE CIERRE (USD) Y VOLÚMENES DIARIOS – 2015–2025
A2: ⚠️ Datos simulados con seed fijo. Para datos reales: Bloomberg → BDH(ticker,"PX_LAST",ini,fin) | BDH(ticker,"PX_VOLUME",ini,fin)
A3: Fecha | B3: Energy | J3: Materials | R3: Financials
A4: Fecha | B4: Precio XOM US | C4: Volumen {t} | D4: Precio CVX US | E4: Volumen {t} | F4: Precio BP LN | G4: Volumen {t} | H4: Precio TTE FP | I4: Volumen {t} | J4: Precio LIN US | K4: Volumen {t} | L4: Precio APD US | M4: Volumen {t} | N4: Precio NEM US | O4: Volumen {t} | P4: Precio FCX US | Q4: Volumen {t} | R4: Precio JPM US | S4: Volumen {t} | T4: Precio BAC US | U4: Volumen {t}
A5: 42006 | B5: 81.88 | C5: 11377547 | D5: 94.9 | E5: 10895356 | F5: 41.95 | G5: 11015879 | H5: 48.21 | I5: 7358390 | J5: 189.56 | K5: 2069530 | L5: 140.43 | M5: 3372669 | N5: 25.2 | O5: 10331521 | P5: 10.91 | Q5: 10434019 | R5: 58.19 | S5: 30653133 | T5: 16.01 | U5: 77448240
A6: 42009 | B6: 82.43 | C6: 6767236 | D6: 94.57 | E6: 10323978 | F6: 42.4 | G6: 18556221 | H6: 48.44 | I6: 8595712 | J6: 191.4 | K6: 1332066 | L6: 141.43 | M6: 1364109 | N6: 24.42 | O6: 8179327 | P6: 10.79 | Q6: 18942055 | R6: 58.67 | S6: 13954106 | T6: 16.18 | U6: 55947132
A7: 42010 | B7: 82.37 | C7: 10941960 | D7: 94.73 | E7: 11210318 | F7: 42.74 | G7: 22099310 | H7: 48.83 | I7: 9148380 | J7: 190.02 | K7: 1569577 | L7: 140.68 | M7: 2874494 | N7: 24.35 | O7: 17007262 | P7: 10.69 | Q7: 10055064 | R7: 59.23 | S7: 31384209 | T7: 16.28 | U7: 100059616
A8: 42011 | B8: 83.8 | C8: 11661501 | D8: 93.14 | E8: 7563393 | F8: 43.24 | G8: 11337929 | H8: 48.86 | I8: 8607769 | J8: 189.35 | K8: 2434179 | L8: 141.7 | M8: 4241056 | N8: 24.54 | O8: 8171789 | P8: 10.62 | Q8: 11257885 | R8: 59.92 | S8: 18258903 | T8: 16.27 | U8: 97983262
A9: 42012 | B9: 83.1 | C9: 10942831 | D9: 91.11 | E9: 6077307 | F9: 42.96 | G9: 22494565 | H9: 49.58 | I9: 7955679 | J9: 190 | K9: 2100781 | L9: 143.59 | M9: 3170016 | N9: 24.63 | O9: 6967167 | P9: 10.74 | Q9: 16714712 | R9: 60.82 | S9: 21802616 | T9: 16.66 | U9: 71386967
A10: 42013 | B10: 84.72 | C10: 12414428 | D10: 90.58 | E10: 5953190 | F10: 42.89 | G10: 28539926 | H10: 50.08 | I10: 9653321 | J10: 184.64 | K10: 2426578 | L10: 144.59 | M10: 2087555 | N10: 24.45 | O10: 9993068 | P10: 10.96 | Q10: 10252046 | R10: 60.53 | S10: 30987779 | T10: 16.58 | U10: 71257964
A11: 42016 | B11: 84.84 | C11: 7531358 | D11: 90.84 | E11: 5734032 | F11: 43.36 | G11: 20019084 | H11: 51.47 | I11: 8674017 | J11: 187.73 | K11: 1218041 | L11: 144.42 | M11: 2742359 | N11: 24.97 | O11: 4957252 | P11: 11.09 | Q11: 17661093 | R11: 61.66 | S11: 26701744 | T11: 16.59 | U11: 67480408
A12: 42017 | B12: 83.59 | C12: 12703521 | D12: 90.66 | E12: 14454721 | F12: 43.06 | G12: 21922351 | H12: 50.51 | I12: 7050889 | J12: 188.37 | K12: 2494376 | L12: 146.97 | M12: 2466888 | N12: 24.64 | O12: 11373551 | P12: 11.17 | Q12: 17212462 | R12: 61.16 | S12: 29480337 | T12: 16.61 | U12: 96795790
A13: 42018 | B13: 84.9 | C13: 14193380 | D13: 91 | E13: 14812547 | F13: 43.2 | G13: 18224214 | H13: 50.6 | I13: 11558644 | J13: 188.69 | K13: 2311626 | L13: 149.12 | M13: 2115356 | N13: 24.14 | O13: 10898269 | P13: 11.2 | Q13: 12263954 | R13: 61.82 | S13: 26009944 | T13: 16.42 | U13: 92437242
A14: 42019 | B14: 84.72 | C14: 6661109 | D14: 91.52 | E14: 8877920 | F14: 42.82 | G14: 23137673 | H14: 50.91 | I14: 6613910 | J14: 189.66 | K14: 2609038 | L14: 147.89 | M14: 2785667 | N14: 24.15 | O14: 16798030 | P14: 10.95 | Q14: 18128777 | R14: 61.61 | S14: 21338696 | T14: 16.8 | U14: 79794244
A15: 42020 | B15: 87.03 | C15: 10408267 | D15: 91.93 | E15: 7674711 | F15: 42.48 | G15: 20374898 | H15: 50.75 | I15: 8485979 | J15: 184.92 | K15: 3201480 | L15: 147.64 | M15: 3807179 | N15: 23.86 | O15: 10877607 | P15: 11.37 | Q15: 11086218 | R15: 60.52 | S15: 18393037 | T15: 16.9 | U15: 96640160
A16: 42023 | B16: 88.4 | C16: 11074755 | D16: 90.19 | E16: 7825419 | F16: 43.12 | G16: 22793975 | H16: 49.57 | I16: 7915876 | J16: 188.08 | K16: 3275928 | L16: 148.68 | M16: 2731976 | N16: 23.52 | O16: 7470271 | P16: 11.38 | Q16: 17264389 | R16: 60.96 | S16: 18843823 | T16: 16.67 | U16: 61333235
... A2676: 45747 | B2676: 129.11 | C2676: 9912568 | D2676: 285.59 | E2676: 13061522 | F2676: 115.55 | G2676: 18560520 | H2676: 156.63 | I2676: 11799426 | J2676: 281.62 | K2676: 2139170 | L2676: 167.22 | M2676: 2108951 | N2676: 33.91 | O2676: 9042251 | P2676: 10.3 | Q2676: 13712445 | R2676: 125.16 | S2676: 14003322 | T2676: 29.35 | U2676: 82747155

Sheet ⚖️ Pesos Índice
A1: PESOS DEL ÍNDICE – ENERO 2015 (día inicial)
A3: PARTE a) – Pesos por Volumen de Transacciones (enero 2015)
A4: Ticker | B4: Sector | C4: Volumen ene-2015 | D4: Peso | E4: Verificación (suma)
A5: XOM US | B5: Energy | C5: 11377547 | D5: 0.065030799 | E5: 1
A6: CVX US | B6: Energy | C6: 10895356 | D6: 0.062274734
A7: BP LN | B7: Energy | C7: 11015879 | D7: 0.062963609
A8: TTE FP | B8: Energy | C8: 7358390 | D8: 0.042058449
A9: LIN US | B9: Materials | C9: 2069530 | D9: 0.011828841
A10: APD US | B10: Materials | C10: 3372669 | D10: 0.01927721
A11: NEM US | B11: Materials | C11: 10331521 | D11: 0.059052014
A12: FCX US | B12: Materials | C12: 10434019 | D12: 0.059637864
A13: JPM US | B13: Financials | C13: 30653133 | D13: 0.17520453
A14: BAC US | B14: Financials | C14: 77448240 | D14: 0.44267195
A15: TOTAL | C15: 174956284 | D15: 1
A17: PARTE b) – Pesos por Precio Inicial (enero 2015)
A18: Ticker | B18: Sector | C18: Precio ene-2015 (USD) | D18: Peso | E18: Verificación (suma)
A19: XOM US | B19: Energy | C19: 81.88 | D19: 0.11577399 | E19: 1
A20: CVX US | B20: Energy | C20: 94.9 | D20: 0.13418359
A21: BP LN | B21: Energy | C21: 41.95 | D21: 0.059315084
A22: TTE FP | B22: Energy | C22: 48.21 | D22: 0.068166393
A23: LIN US | B23: Materials | C23: 189.56 | D23: 0.26802783
A24: APD US | B24: Materials | C24: 140.43 | D24: 0.1985606
A25: NEM US | B25: Materials | C25: 25.2 | D25: 0.035631469
A26: FCX US | B26: Materials | C26: 10.91 | D26: 0.015426164
A27: JPM US | B27: Financials | C27: 58.19 | D27: 0.082277586
A28: BAC US | B28: Financials | C28: 16.01 | D28: 0.022637294
A29: TOTAL | C29: 707.24 | D29: 1
A31: 📊 Comparación: ¿Cómo cambian los pesos y por qué?
A32: • Pesos por VOLUMEN reflejan liquidez: BAC (80M acc/día) domina aunque su precio sea bajo.
A33: • Pesos por PRECIO favorecen acciones caras: LIN ($190) y APD ($140) tienen pesos altos sin importar su volumen.
A34: • El Dow Jones es price-weighted → muy sensible a splits de acciones y a movimientos de empresas caras.
A35: • Un índice value-weighted (como S&P 500) pondera por capitalización, no solo precio.
A36: • Conclusión: los pesos por volumen son más representativos de la actividad real del mercado.

Sheet 📈 Retornos
A1: RETORNOS ARITMÉTICOS DIARIOS Y RETORNOS PONDERADOS POR ÍNDICE
A2: Fórmula: Rt = (Pt − Pt-1)/Pt-1 | Ret. Ponderado = Σ(wi × Ri) | Azul = input | Naranja = retorno ponderado
A3: Fecha | B3: Índice Energy | G3: Índice Materials | L3: Índice Financials
A4: Fecha | B4: Ret. XOM US | C4: Ret. CVX US | D4: Ret. BP LN | E4: Ret. TTE FP | F4: Ret.Pond. Energy | G4: Ret. LIN US | H4: Ret. APD US | I4: Ret. NEM US | J4: Ret. FCX US | K4: Ret.Pond. Materials | L4: Ret. JPM US | M4: Ret. BAC US | N4: Ret.Pond. Financials
A5: 42009 | B5: 0.006717147 | C5: -0.0034773446 | D5: 0.010727056 | E5: 0.0047707944 | F5: 0.0047189277 | G5: 0.0097066892 | H5: 0.0071209855 | I5: -0.030952381 | J5: -0.010999083 | K5: -0.014898073 | L5: 0.00824884 | M5: 0.010618364 | N5: 0.0099464635
A6: 42010 | B6: -0.00072789033 | C6: 0.0016918685 | D6: 0.0080188679 | E6: 0.0080511974 | F6: 0.0038804823 | G6: -0.0072100313 | H6: -0.0053029767 | I6: -0.0028665029 | J6: -0.0092678406 | K6: -0.0060715929 | L6: 0.0095449122 | M6: 0.0061804697 | N6: 0.0071344882
A7: 42011 | B7: 0.01736069 | C7: -0.016784546 | D7: 0.011698643 | E7: 0.00061437641 | F7: 0.0036420767 | G7: -0.0035259446 | H7: 0.0072504976 | I7: 0.0078028747 | J7: -0.0065481759 | K7: 0.0011236472 | L7: 0.011649502 | M7: -0.00061425061 | N7: 0.0028632486
A8: 42012 | B8: -0.008353222 | C8: -0.021795147 | D8: -0.0064754857 | E8: 0.01473598 | F8: -0.0072675447 | G8: 0.0034327964 | H8: 0.013338038 | I8: 0.0036674817 | J8: 0.011299435 | K8: 0.0079319413 | L8: 0.015020027 | M8: 0.023970498 | N8: 0.02143251
A9: 42013 | B9: 0.019494585 | C9: -0.0058171441 | D9: -0.0016294227 | E9: 0.010084712 | F9: 0.0052815093 | G9: -0.028210526 | H9: 0.0069642733 | I9: -0.0073081608 | J9: 0.020484171 | K9: 0.0039428611 | L9: -0.0047681684 | M9: -0.0048019208 | N9: -0.00479235
A10: 42016 | B10: 0.0014164306 | C10: 0.0028703908 | D10: 0.010958265 | E10: 0.027755591 | F10: 0.0091603131 | G10: 0.016735269 | H10: -0.0011757383 | I10: 0.021267894 | J10: 0.011861314 | K10: 0.014276685 | L10: 0.018668429 | M10: 0.00060313631 | N10: 0.0057257152
A11: 42017 | B11: -0.014733616 | C11: -0.0019815059 | D11: -0.0069188192 | E11: -0.018651642 | F11: -0.0099068283 | G11: 0.0034091514 | H11: 0.017656834 | I11: -0.013215859 | J11: 0.007213706 | K11: 0.00020352841 | L11: -0.0081089848 | M11: 0.0012055455 | N11: -0.0014356747
A12: 42018 | B12: 0.015671731 | C12: 0.0037502758 | D12: 0.0032512773 | E12: 0.0017818254 | F12: 0.0065956246 | G12: 0.0016987843 | H12: 0.014628836 | I12: -0.020292208 | J12: 0.0026857654 | K12: -0.0049135157 | L12: 0.010791367 | M12: -0.011438892 | N12: -0.0051352989
A13: 42019 | B13: -0.0021201413 | C13: 0.0057142857 | D13: -0.0087962963 | E13: 0.0061264822 | F13: -0.00033657251 | G13: 0.005140707 | H13: -0.0082483906 | I13: 0.00041425021 | J13: -0.022321429 | K13: -0.009379009 | L13: -0.0033969589 | M13: 0.023142509 | N13: 0.015617
A14: 42020 | B14: 0.027266289 | C14: 0.0044798951 | D14: -0.0079402149 | E14: -0.003142801 | F14: 0.006112089 | G14: -0.024992091 | H14: -0.0016904456 | I14: -0.012008282 | J14: 0.038356164 | K14: 0.0083457004 | L14: -0.017691933 | M14: 0.005952381 | N14: -0.00075218055
A15: 42023 | B15: 0.015741698 | C15: -0.018927445 | D15: 0.015065913 | E15: -0.023251232 | F15: -0.00079333165 | G15: 0.017088471 | H15: 0.0070441615 | I15: -0.01424979 | J15: 0.00087950748 | K15: -0.003011419 | L15: 0.0072703239 | M15: -0.013609467 | N15: -0.0076888117
A16: 42024 | B16: -0.013574661 | C16: -0.027386628 | D16: 0.0057977737 | E16: 0.0012104095 | F16: -0.0093501994 | G16: -0.0044661846 | H16: -0.0078019909 | I16: 0.011904762 | J16: 0.040421793 | K16: 0.019429361 | L16: 0.0078740157 | M16: -0.0023995201 | N16: 0.00051363495
... A2675: 45747 | B2675: -0.0068461538 | C2675: -0.00038501925 | D2675: -0.0043942788 | E2675: -0.0076031173 | F2675: -0.0045868112 | G2675: 0.0061809997 | H2675: -0.0048797905 | I2675: -0.012809316 | J2675: -0.0029041626 | K2675: -0.0063457576 | L2675: 0.0091920658 | M2675: 0.010327022 | N2675: 0.010005195

Sheet 🦠 Análisis COVID
A1: ANÁLISIS COVID – PRE (2015–2019) vs POST (2020–2025)
A2: Corte: 01-ene-2020 | IC 95% con CONFIDENCE.T | Fórmulas en negro, inputs en azul
A4: ÍNDICE ENERGY
A5: Período | B5: N (obs.) | C5: Media (%) | D5: Desv. Est. (%) | E5: Error Est. (%) | F5: IC 95% inferior | G5: IC 95% superior | H5: Amplitud IC
A6: Pre-COVID (2015–2019) | B6: =COUNTA('📈 Retornos'!F5:F1306) -> 1302 | C6: =AVERAGE('📈 Retornos'!F5:F1306) -> 0.00032221669 | D6: =STDEV('📈 Retornos'!F5:F1306) -> 0.0063554652 | E6: =D6/SQRT(B6) -> 0.00017613345 | F6: =_xludf.CONFIDENCE.T(0.05,D6,B6) -> #NAME? | G6: =C6-F6 -> #NAME? | H6: =C6+F6 -> #NAME? | I6: =H6-G6 -> #NAME?
A7: Post-COVID (2020–2025) | B7: =COUNTA('📈 Retornos'!F1307:F2675) -> 1369 | C7: =AVERAGE('📈 Retornos'!F1307:F2675) -> 0.00051362931 | D7: =STDEV('📈 Retornos'!F1307:F2675) -> 0.0073128641 | E7: =D7/SQRT(B7) -> 0.00019764498 | F7: =_xludf.CONFIDENCE.T(0.05,D7,B7) -> #NAME? | G7: =C7-F7 -> #NAME? | H7: =C7+F7 -> #NAME? | I7: =H7-G7 -> #NAME?
A8: Diferencia (Post−Pre) | C8: =C7-C6 -> 0.00019141262 | D8: =D7-D6 -> 0.00095739889
A10: ÍNDICE MATERIALS
A11: Período | B11: N (obs.) | C11: Media (%) | D11: Desv. Est. (%) | E11: Error Est. (%) | F11: IC 95% inferior | G11: IC 95% superior | H11: Amplitud IC
A12: Pre-COVID (2015–2019) | B12: =COUNTA('📈 Retornos'!K5:K1306) -> 1302 | C12: =AVERAGE('📈 Retornos'!K5:K1306) -> 0.00013659522 | D12: =STDEV('📈 Retornos'!K5:K1306) -> 0.0069950236 | E12: =D12/SQRT(B12) -> 0.00019385798 | F12: =_xludf.CONFIDENCE.T(0.05,D12,B12) -> #NAME? | G12: =C12-F12 -> #NAME? | H12: =C12+F12 -> #NAME? | I12: =H12-G12 -> #NAME?
A13: Post-COVID (2020–2025) | B13: =COUNTA('📈 Retornos'!K1307:K2675) -> 1369 | C13: =AVERAGE('📈 Retornos'!K1307:K2675) -> 0.00013129104 | D13: =STDEV('📈 Retornos'!K1307:K2675) -> 0.0081470393 | E13: =D13/SQRT(B13) -> 0.00022019025 | F13: =_xludf.CONFIDENCE.T(0.05,D13,B13) -> #NAME? | G13: =C13-F13 -> #NAME? | H13: =C13+F13 -> #NAME? | I13: =H13-G13 -> #NAME?
A14: Diferencia (Post−Pre) | C14: =C13-C12 -> -5.3041839e-06 | D14: =D13-D12 -> 0.0011520157
A16: ÍNDICE FINANCIALS
A17: Período | B17: N (obs.) | C17: Media (%) | D17: Desv. Est. (%) | E17: Error Est. (%) | F17: IC 95% inferior | G17: IC 95% superior | H17: Amplitud IC
A18: Pre-COVID (2015–2019) | B18: =COUNTA('📈 Retornos'!N5:N1306) -> 1302 | C18: =AVERAGE('📈 Retornos'!N5:N1306) -> 0.00024685402 | D18: =STDEV('📈 Retornos'!N5:N1306) -> 0.0089493241 | E18: =D18/SQRT(B18) -> 0.00024801888 | F18: =_xludf.CONFIDENCE.T(0.05,D18,B18) -> #NAME? | G18: =C18-F18 -> #NAME? | H18: =C18+F18 -> #NAME? | I18: =H18-G18 -> #NAME?
A19: Post-COVID (2020–2025) | B19: =COUNTA('📈 Retornos'!N1307:N2675) -> 1369 | C19: =AVERAGE('📈 Retornos'!N1307:N2675) -> 0.00039714339 | D19: =STDEV('📈 Retornos'!N1307:N2675) -> 0.010427925 | E19: =D19/SQRT(B19) -> 0.00028183582 | F19: =_xludf.CONFIDENCE.T(0.05,D19,B19) -> #NAME? | G19: =C19-F19 -> #NAME? | H19: =C19+F19 -> #NAME? | I19: =H19-G19 -> #NAME?
A20: Diferencia (Post−Pre) | C20: =C19-C18 -> 0.00015028937 | D20: =D19-D18 -> 0.0014786011
A22: 📝 INTERPRETACIÓN: ¿Hay evidencia de cambio antes y después del COVID?
A23: 1. Si los IC 95% pre y post COVID NO se solapan → evidencia estadística de cambio en retornos medios.
A24: 2. La desviación estándar post-COVID es generalmente mayor → mercados más volátiles tras la pandemia.
A25: 3. Energy: crash por precios negativos del petróleo (abr-2020). Recuperación tardía vs otros sectores.
A26: 4. Materials: resiliencia relativa por demanda de metales en transición energética; cobre (FCX) muy fuerte en 2021.
A27: 5. Financials: golpeados en 2020 por riesgo de crédito; fuerte recuperación en 2022 con subida de tasas (NIM↑).
A28: 6. Conclusión general: SÍ hay cambio estructural post-COVID en medias y volatilidades de los tres índices.

Sheet 📝 Descripción Índice
A1: PARTE 3a – DESCRIPCIÓN DEL ÍNDICE: NATURALEZA, SECTORES E INDUSTRIAS
A3: COMPOSICIÓN GENERAL
A4: El índice está compuesto por 10 acciones en 3 sectores del S&P 500 y mercados europeos (LSE, Euronext París). Cubre el período enero 2015 – marzo 2025, permitiendo analizar el comportamiento antes y después del COVID-19. Los tres sectores representan segmentos diferenciados de la economía real: energía, insumos industriales y servicios financieros.
A8: SECTOR ENERGY – 4 acciones
A9: • ExxonMobil (XOM US) → Mayor petrolera integrada de EEUU; upstream en Permian Basin, downstream global. • Chevron (CVX US) → 2ª energética de EEUU; fuerte posición en gas natural licuado (GNL). • BP (BP LN) → Británica diversificada en petróleo, gas y energías renovables (offshore wind). • TotalEnergies (TTE FP)→ Francesa; líder en GNL y una de las más avanzadas en transición energética (solar, eólica).
A14: SECTOR MATERIALS – 4 acciones
A15: • Linde (LIN US) → Líder mundial en gases industriales; perfil defensivo y de alto crecimiento. • Air Products (APD US) → Gases industriales con enfoque estratégico en hidrógeno limpio (H₂). • Newmont (NEM US) → Mayor minera de oro del mundo; activo refugio en períodos de crisis. • Freeport-McMoRan (FCX) → Mayor productora de cobre; altamente cíclica, expuesta a China y transición energética.
A20: SECTOR FINANCIALS – 2 acciones
A21: • JPMorgan Chase (JPM US) → Mayor banco de EEUU por activos; banca de inversión, retail y gestión de activos. • Bank of America (BAC US)→ 2º banco de EEUU; muy sensible a la curva de tasas (NIM = margen neto de interés).
A24: METODOLOGÍA DE PONDERACIÓN
A25: Se calculan dos tipos de pesos usando datos del primer día disponible (ene-2015): 1. Por volumen: refleja liquidez y actividad real (similar a índices value-weighted como el S&P 500). 2. Por precio: similar al Dow Jones Industrial Average; sensible a stocks splits y precio absoluto. El índice ponderado por volumen es más representativo de la capitalización relativa de cada empresa.
A30: EVENTOS CLAVE DEL PERÍODO 2015–2025
A31: 2015–2016 : Caída del petróleo → impacto negativo en Energy; FCX cae por crash de materias primas. 2018 : Tensiones EEUU-China → volatilidad en Materials (cobre, oro). Subida de tasas Fed → NIM↑ en Financials. Feb-Mar 2020: Crash COVID-19 → caída del 30–40% en semanas en todos los sectores. 2020-2021 : Recuperación en V; Energy rezagado. Materials y Financials lideran el rebote. 2022 : Inflación + subida agresiva de tasas → Financials mejora NIM; Energy al alza (guerra Ucrania). 2023-2025 : Normalización; debate transición energética presiona a Energy; Materials mixto por ciclo China.

Sheet 📊 Gráficos
A1: GRÁFICOS DEL TALLER 5 – ANÁLISIS VISUAL COMPLETO
A3: e) LÍNEA BASE 100 – Índices Ponderados Acumulados (ene-2015=100)
A27: 📝 Análisis: Muestra la evolución acumulada de cada índice desde base 100. Observar: crash COVID (mar-2020), recuperación asimétrica por sector, tendencias 2022–2025.
A33: c) BOX & WHISKER – Retornos Diarios Ponderados por Índice
A57: 📝 Análisis: Compara la distribución de retornos pre y post COVID. Notar: mayor dispersión post-COVID (volatilidad), valores atípicos (outliers) más extremos durante el crash.
A63: d) HISTOGRAMA – Retornos con Curva Normal de Referencia
A87: 📝 Análisis: Analiza la forma de la distribución: skewness (sesgo) y kurtosis (colas pesadas / fat tails). Los mercados financieros tienen kurtosis > 3 (leptocúrtica).
A93: 4c) BARRAS CON IC 95% – Retorno Medio Pre vs Post COVID
A117: 📝 Análisis: Compara las medias con intervalos de confianza. Si los IC NO se solapan → cambio estadísticamente significativo en retornos medios al 95% de confianza.
